pyNutEmail/__init__.py
pyNutEmail/_lib.py
pyNutEmail/nutEmail.py
pynut_Email-2.1.4.dist-info/LICENSE
pynut_Email-2.1.4.dist-info/METADATA
pynut_Email-2.1.4.dist-info/WHEEL
pynut_Email-2.1.4.dist-info/top_level.txt
pynut_Email-2.1.4.dist-info/RECORD
